globconf/__init__.py
test/__init__.py
test/test_verify_required_options.py
klang_globconf-0.0.6.dist-info/LICENSE.md
klang_globconf-0.0.6.dist-info/METADATA
klang_globconf-0.0.6.dist-info/WHEEL
klang_globconf-0.0.6.dist-info/top_level.txt
klang_globconf-0.0.6.dist-info/RECORD
