Metadata-Version: 2.1
Name: klang-globconf
Version: 0.0.6
Summary: global configparser object to be used across modules
Home-page: https://github.com/steffenschumacher/globconf
Author: Steffen Schumacher
Author-email: ssch@wheel.dk
License: UNKNOWN
Platform: UNKNOWN
Classifier: Programming Language :: Python :: 3
Classifier: License :: OSI Approved :: MIT License
Classifier: Operating System :: OS Independent
